README.md
setup.cfg
setup.py
ytpy/__init__.py
ytpy/config.py
ytpy/entity.py
ytpy/exceptions.py
ytpy/utils.py
ytpy/youtube.py
ytpy.egg-info/PKG-INFO
ytpy.egg-info/SOURCES.txt
ytpy.egg-info/dependency_links.txt
ytpy.egg-info/requires.txt
ytpy.egg-info/top_level.txt