Metadata-Version: 2.1
Name: ytpy
Version: 2020.10.9.1
Summary: Python asynchronous wrapper for youtube data api v3.
Home-page: https://github.com/madeyoga/ytpy
Author: yeogaa
Author-email: yeogaa02@gmail.com
License: UNKNOWN
Keywords: youtube-api-v3 python youtube-search asynchronous
Platform: UNKNOWN
